LICENSE.txt
README.md
setup.cfg
setup.py
bfa_fiscal/__init__.py
bfa_fiscal/comprobante.py
bfa_fiscal/handler.py
bfa_fiscal/padron.py
bfa_fiscal.egg-info/PKG-INFO
bfa_fiscal.egg-info/SOURCES.txt
bfa_fiscal.egg-info/dependency_links.txt
bfa_fiscal.egg-info/requires.txt
bfa_fiscal.egg-info/top_level.txt