Metadata-Version: 1.1
Name: bfa-fiscal
Version: 1.1.1
Summary: Paquete de conectividad con los servicios web de AFIP
Home-page: http://www.basisty.com
Author: German Basisty
Author-email: german.basisty@basisty.com
License: GPLv3
Keywords: afip,Fiscal
Platform: UNKNOWN
Classifier: Development Status :: 5 - Production/Stable
Classifier: Intended Audience :: Developers
Classifier: Topic :: Software Development :: Build Tools
Classifier: License :: OSI Approved :: MIT License
Classifier: Programming Language :: Python :: 3
Classifier: Programming Language :: Python :: 3.4
Classifier: Programming Language :: Python :: 3.5
Classifier: Programming Language :: Python :: 3.6
Classifier: Programming Language :: Python :: 3.7
Classifier: Programming Language :: Python :: 3.8
